MANIFEST.in
README.md
built_info.json
setup.py
colabo_flow.s_go.egg-info/PKG-INFO
colabo_flow.s_go.egg-info/SOURCES.txt
colabo_flow.s_go.egg-info/dependency_links.txt
colabo_flow.s_go.egg-info/not-zip-safe
colabo_flow.s_go.egg-info/requires.txt
colabo_flow.s_go.egg-info/top_level.txt
colabo_flow/s_go/__init__.py
colabo_flow/s_go/concurrency.py
colabo_flow/s_go/config.py
colabo_flow/s_go/django.py
colabo_flow/s_go/executor_operators.py
colabo_flow/s_go/executor_vos.py
colabo_flow/s_go/go_amqp_client.py
colabo_flow/s_go/go_amqp_host.py
colabo_flow/s_go/operators.py
colabo_flow/s_go/vos.py