Metadata-Version: 2.1
Name: colabo-flow.s-go
Version: 0.3.4
Summary: A python ColaboFlow.Go (CF.Go) puzzle for supporting execution of workflow tasks over the RabbitMQ broker
Home-page: https://github.com/Cha-OS/
Author: ChaOS
Author-email: chaos.ngo@gmail.com
License: MIT
Project-URL: website, http://colabo.space
Project-URL: organization, http://cha-os.org
Keywords: colabo,RabbitMQ,flow,colaboflow,go,process,workflow
